pbixrefresher/__init__.py
pbixrefresher/pbixrefresher.py
pbixrefresher-0.1.8.dist-info/DESCRIPTION.rst
pbixrefresher-0.1.8.dist-info/METADATA
pbixrefresher-0.1.8.dist-info/RECORD
pbixrefresher-0.1.8.dist-info/WHEEL
pbixrefresher-0.1.8.dist-info/entry_points.txt
pbixrefresher-0.1.8.dist-info/metadata.json
pbixrefresher-0.1.8.dist-info/top_level.txt
