Metadata-Version: 2.0
Name: pbixrefresher
Version: 0.1.8
Summary: Script for refreshing and publishing Power BI workbooks
Home-page: https://github.com/dubravcik/pbixrefresher-python
Author: Michal Dubravcik
Author-email: michal.dubravcik@gmail.com
License: MIT
Platform: UNKNOWN
Requires-Dist: pywinauto
Requires-Dist: psutil
